simple_ai/__init__.py
simple_ai/__main__.py
simple_ai/api/grpc/chat/client.py
simple_ai/api/grpc/chat/llm_chat_pb2.py
simple_ai/api/grpc/chat/llm_chat_pb2.pyi
simple_ai/api/grpc/chat/llm_chat_pb2_grpc.py
simple_ai/api/grpc/chat/model.py
simple_ai/api/grpc/chat/server.py
simple_ai/api/grpc/completion/client.py
simple_ai/api/grpc/completion/llm_pb2.py
simple_ai/api/grpc/completion/llm_pb2.pyi
simple_ai/api/grpc/completion/llm_pb2_grpc.py
simple_ai/api/grpc/completion/model.py
simple_ai/api/grpc/completion/server.py
simple_ai/api/grpc/embedding/client.py
simple_ai/api/grpc/embedding/llm_embed_pb2.py
simple_ai/api/grpc/embedding/llm_embed_pb2.pyi
simple_ai/api/grpc/embedding/llm_embed_pb2_grpc.py
simple_ai/api/grpc/embedding/model.py
simple_ai/api/grpc/embedding/server.py
simple_ai/api/grpc/protos/images.proto
simple_ai/api/grpc/protos/llm_chat.proto
simple_ai/api/grpc/protos/llm_complete.proto
simple_ai/api/grpc/protos/llm_embed.proto
simple_ai/api_models.py
simple_ai/dummy.py
simple_ai/models.py
simple_ai/models.toml
simple_ai/models.toml.template
simple_ai/server.py
simple_ai/utils.py
simple_ai_server-0.2.1.dist-info/entry_points.txt
simple_ai_server-0.2.1.dist-info/LICENSE
simple_ai_server-0.2.1.dist-info/METADATA
simple_ai_server-0.2.1.dist-info/WHEEL
simple_ai_server-0.2.1.dist-info/RECORD
