Metadata-Version: 2.1
Name: simple-ai-server
Version: 0.2.1
Summary: 
Author: Louis Hénault
Requires-Python: >=3.9,<4.0
Classifier: Programming Language :: Python :: 3
Classifier: Programming Language :: Python :: 3.9
Classifier: Programming Language :: Python :: 3.10
Classifier: Programming Language :: Python :: 3.11
Requires-Dist: fastapi (>=0.94.1,<0.95.0)
Requires-Dist: grpcio (>=1.51.3,<2.0.0)
Requires-Dist: protobuf (>=4.21.3,<5.0.0)
Requires-Dist: tomli (>=2.0.1,<3.0.0) ; python_version < "3.11"
Requires-Dist: uvicorn (>=0.21.0,<0.22.0)
